Tensorflow20DeXinzengGongnengChuyiFix1/README.md
Tensorflow20DeXinzengGongnengChuyiFix1/__init__.py
Tensorflow20DeXinzengGongnengChuyiFix1/__main__.py
Tensorflow20DeXinzengGongnengChuyiFix1/file.epub
Tensorflow20DeXinzengGongnengChuyiFix1/index.html
Tensorflow20DeXinzengGongnengChuyiFix1/css/__init__.py
Tensorflow20DeXinzengGongnengChuyiFix1/css/annotations.css
Tensorflow20DeXinzengGongnengChuyiFix1/css/main.css
Tensorflow20DeXinzengGongnengChuyiFix1/css/normalize.css
Tensorflow20DeXinzengGongnengChuyiFix1/css/popup.css
Tensorflow20DeXinzengGongnengChuyiFix1/font/__init__.py
Tensorflow20DeXinzengGongnengChuyiFix1/font/fontello.eot
Tensorflow20DeXinzengGongnengChuyiFix1/font/fontello.svg
Tensorflow20DeXinzengGongnengChuyiFix1/font/fontello.ttf
Tensorflow20DeXinzengGongnengChuyiFix1/font/fontello.woff
Tensorflow20DeXinzengGongnengChuyiFix1/img/__init__.py
Tensorflow20DeXinzengGongnengChuyiFix1/img/annotator-glyph-sprite.png
Tensorflow20DeXinzengGongnengChuyiFix1/img/annotator-icon-sprite.png
Tensorflow20DeXinzengGongnengChuyiFix1/img/apple-touch-icon.png
Tensorflow20DeXinzengGongnengChuyiFix1/img/cancelfullscreen.png
Tensorflow20DeXinzengGongnengChuyiFix1/img/close.png
Tensorflow20DeXinzengGongnengChuyiFix1/img/fullscreen.png
Tensorflow20DeXinzengGongnengChuyiFix1/img/loader.gif
Tensorflow20DeXinzengGongnengChuyiFix1/img/menu-icon.png
Tensorflow20DeXinzengGongnengChuyiFix1/img/save.png
Tensorflow20DeXinzengGongnengChuyiFix1/img/saved.png
Tensorflow20DeXinzengGongnengChuyiFix1/img/settings-s.png
Tensorflow20DeXinzengGongnengChuyiFix1/img/settings.png
Tensorflow20DeXinzengGongnengChuyiFix1/img/star.png
Tensorflow20DeXinzengGongnengChuyiFix1/js/__init__.py
Tensorflow20DeXinzengGongnengChuyiFix1/js/epub.js
Tensorflow20DeXinzengGongnengChuyiFix1/js/epub.min.js
Tensorflow20DeXinzengGongnengChuyiFix1/js/epub.min.map
Tensorflow20DeXinzengGongnengChuyiFix1/js/hooks.min.js
Tensorflow20DeXinzengGongnengChuyiFix1/js/hooks.min.map
tensorflow_2_0_de_xinzeng_gongneng_chuyi_fix1-2025.3.25.0.dist-info/METADATA
tensorflow_2_0_de_xinzeng_gongneng_chuyi_fix1-2025.3.25.0.dist-info/WHEEL
tensorflow_2_0_de_xinzeng_gongneng_chuyi_fix1-2025.3.25.0.dist-info/entry_points.txt
tensorflow_2_0_de_xinzeng_gongneng_chuyi_fix1-2025.3.25.0.dist-info/top_level.txt
tensorflow_2_0_de_xinzeng_gongneng_chuyi_fix1-2025.3.25.0.dist-info/RECORD
